{
  "quotes": {
    "NQ=F": {
      "price": 29113.75,
      "change": -67.5,
      "pct": -0.23
    },
    "CL=F": {
      "price": 88.22,
      "change": 1.39,
      "pct": 1.6
    },
    "JPY=X": {
      "price": 163.07,
      "change": -0.06,
      "pct": -0.0368
    },
    "^TNX": {
      "price": 4.663,
      "change": 0.006,
      "pct": 0.1288
    },
    "^TYX": {
      "price": 5.151,
      "change": 0.004,
      "pct": 0.0777
    },
    "DX-Y.NYB": {
      "price": 100.965,
      "change": -0.16,
      "pct": -0.16
    },
    "^VIX": {
      "price": 16.64,
      "change": -0.41,
      "pct": -2.4
    }
  },
  "errors": [],
  "fetched_at": "2026-07-23T14:14:40+09:00",
  "jpy_carry": {
    "peak_3mo": 163.07,
    "warn_level": 158.18,
    "drop_pct": 0.0,
    "warning": false
  }
}