{
  "quotes": {
    "NQ=F": {
      "price": 29605.25,
      "change": -119.5,
      "pct": -0.4
    },
    "CL=F": {
      "price": 69.31,
      "change": -2.61,
      "pct": -3.63
    },
    "JPY=X": {
      "price": 161.76,
      "change": -0.03,
      "pct": -0.02
    },
    "^TNX": {
      "price": 4.369,
      "change": -0.02,
      "pct": -0.46
    },
    "^TYX": {
      "price": 4.866,
      "change": 0.007,
      "pct": 0.14
    },
    "DX-Y.NYB": {
      "price": 101.33,
      "change": -0.13,
      "pct": -0.13
    }
  },
  "errors": [],
  "fetched_at": "2026-06-27T02:00:03+09:00"
}