{
  "quotes": {
    "NQ=F": {
      "price": 29632.0,
      "change": -400.25,
      "pct": -1.33
    },
    "CL=F": {
      "price": 75.07,
      "change": 3.66,
      "pct": 5.13
    },
    "JPY=X": {
      "price": 162.37,
      "change": 0.67,
      "pct": 0.41
    },
    "^TNX": {
      "price": 4.604,
      "change": 0.035,
      "pct": 0.77
    },
    "^TYX": {
      "price": 5.094,
      "change": 0.023,
      "pct": 0.45
    },
    "DX-Y.NYB": {
      "price": 101.15,
      "change": 0.2,
      "pct": 0.2
    }
  },
  "errors": [],
  "fetched_at": "2026-07-14T01:21:29+09:00"
}