{
  "quotes": {
    "NQ=F": {
      "price": 29439.0,
      "change": -36.75,
      "pct": -0.12
    },
    "CL=F": {
      "price": 79.48,
      "change": 1.34,
      "pct": 1.71
    },
    "JPY=X": {
      "price": 162.33,
      "change": -0.07,
      "pct": -0.04
    },
    "^TNX": {
      "price": 4.62,
      "change": 0.01,
      "pct": 0.22
    },
    "^TYX": {
      "price": 5.103,
      "change": 0.005,
      "pct": 0.1
    },
    "DX-Y.NYB": {
      "price": 101.2,
      "change": -0.09,
      "pct": -0.09
    }
  },
  "errors": [],
  "fetched_at": "2026-07-14T11:52:21+09:00"
}