{
  "quotes": {
    "NQ=F": {
      "price": 29572.5,
      "change": 96.75,
      "pct": 0.33
    },
    "CL=F": {
      "price": 81.01,
      "change": 2.87,
      "pct": 3.67
    },
    "JPY=X": {
      "price": 162.37,
      "change": -0.03,
      "pct": -0.02
    },
    "^TNX": {
      "price": 4.63,
      "change": 0.02,
      "pct": 0.43
    },
    "^TYX": {
      "price": 5.107,
      "change": 0.009,
      "pct": 0.18
    },
    "DX-Y.NYB": {
      "price": 101.16,
      "change": -0.13,
      "pct": -0.13
    }
  },
  "errors": [],
  "fetched_at": "2026-07-14T17:07:58+09:00"
}