{
  "quotes": {
    "NQ=F": {
      "price": 30008.75,
      "change": 640.5,
      "pct": 2.18
    },
    "CL=F": {
      "price": 70.94,
      "change": 1.71,
      "pct": 2.47
    },
    "JPY=X": {
      "price": 161.93,
      "change": 0.17,
      "pct": 0.11
    },
    "^TNX": {
      "price": 4.377,
      "change": 0.008,
      "pct": 0.18
    },
    "^TYX": {
      "price": 4.857,
      "change": -0.008,
      "pct": -0.16
    },
    "DX-Y.NYB": {
      "price": 101.09,
      "change": -0.27,
      "pct": -0.27
    }
  },
  "errors": [],
  "fetched_at": "2026-06-30T03:01:00+09:00"
}