{
  "quotes": {
    "NQ=F": {
      "price": 29763.25,
      "change": -269.0,
      "pct": -0.9
    },
    "CL=F": {
      "price": 73.8,
      "change": 2.39,
      "pct": 3.35
    },
    "JPY=X": {
      "price": 162.12,
      "change": 0.42,
      "pct": 0.26
    },
    "^TNX": {
      "price": 4.574,
      "change": 0.005,
      "pct": 0.11
    },
    "^TYX": {
      "price": 5.079,
      "change": 0.008,
      "pct": 0.16
    },
    "DX-Y.NYB": {
      "price": 100.92,
      "change": -0.03,
      "pct": -0.03
    }
  },
  "errors": [],
  "fetched_at": "2026-07-13T21:02:43+09:00"
}