{
  "quotes": {
    "NQ=F": {
      "price": 29175.75,
      "change": 397.0,
      "pct": 1.38
    },
    "CL=F": {
      "price": 82.81,
      "change": -0.42,
      "pct": -0.5
    },
    "JPY=X": {
      "price": 162.65,
      "change": 0.16,
      "pct": 0.1
    },
    "^TNX": {
      "price": 4.592,
      "change": -0.006,
      "pct": -0.1305
    },
    "^TYX": {
      "price": 5.117,
      "change": -0.001,
      "pct": -0.0195
    },
    "DX-Y.NYB": {
      "price": 100.92,
      "change": -0.029,
      "pct": -0.03
    }
  },
  "errors": [],
  "fetched_at": "2026-07-21T18:23:45+09:00"
}