{
  "quotes": {
    "NQ=F": {
      "price": 29416.0,
      "change": -48.75,
      "pct": -0.17
    },
    "CL=F": {
      "price": 86.48,
      "change": -1.23,
      "pct": -1.4
    },
    "JPY=X": {
      "price": 160.3,
      "change": 0.39,
      "pct": 0.24
    },
    "^TNX": {
      "price": 4.494,
      "change": 0.033,
      "pct": 0.74
    },
    "^TYX": {
      "price": 4.981,
      "change": 0.029,
      "pct": 0.59
    }
  },
  "errors": [],
  "fetched_at": "2026-06-12T22:48:41+09:00"
}