{
  "quotes": {
    "NQ=F": {
      "price": 30599.0,
      "change": -120.75,
      "pct": -0.39
    },
    "CL=F": {
      "price": 76.85,
      "change": 0.25,
      "pct": 0.33
    },
    "JPY=X": {
      "price": 161.3,
      "change": -0.07,
      "pct": -0.04
    },
    "^TNX": {
      "price": 4.463,
      "change": 0.0,
      "pct": 0.0
    },
    "^TYX": {
      "price": 4.9,
      "change": -0.001,
      "pct": -0.02
    }
  },
  "errors": [],
  "fetched_at": "2026-06-19T19:32:50+09:00"
}