{
  "quotes": {
    "NQ=F": {
      "price": 30410.5,
      "change": 411.75,
      "pct": 1.37
    },
    "CL=F": {
      "price": 74.82,
      "change": -1.97,
      "pct": -2.57
    },
    "JPY=X": {
      "price": 160.71,
      "change": 0.05,
      "pct": 0.03
    },
    "^TNX": {
      "price": 4.439,
      "change": -0.018,
      "pct": -0.4
    },
    "^TYX": {
      "price": 4.881,
      "change": -0.046,
      "pct": -0.93
    }
  },
  "errors": [],
  "fetched_at": "2026-06-18T18:21:44+09:00"
}