{
  "quotes": {
    "NQ=F": {
      "price": 29790.75,
      "change": 0.5,
      "pct": 0.0
    },
    "CL=F": {
      "price": 79.94,
      "change": 0.6,
      "pct": 0.76
    },
    "JPY=X": {
      "price": 162.22,
      "change": 0.05,
      "pct": 0.03
    },
    "^TNX": {
      "price": 4.589,
      "change": 0.005,
      "pct": 0.11
    },
    "^TYX": {
      "price": 5.102,
      "change": 0.008,
      "pct": 0.16
    },
    "DX-Y.NYB": {
      "price": 100.92,
      "change": -0.01,
      "pct": -0.01
    }
  },
  "errors": [],
  "fetched_at": "2026-07-15T08:15:57+09:00"
}