{
  "quotes": {
    "NQ=F": {
      "price": 29817.75,
      "change": 151.75,
      "pct": 0.51
    },
    "CL=F": {
      "price": 73.0,
      "change": -0.21,
      "pct": -0.29
    },
    "JPY=X": {
      "price": 161.63,
      "change": 0.12,
      "pct": 0.07
    },
    "^TNX": {
      "price": 4.477,
      "change": -0.011,
      "pct": -0.25
    },
    "^TYX": {
      "price": 4.943,
      "change": 0.001,
      "pct": 0.02
    },
    "DX-Y.NYB": {
      "price": 101.43,
      "change": 0.05,
      "pct": 0.05
    }
  },
  "errors": [],
  "fetched_at": "2026-06-24T15:10:30+09:00"
}