{
  "quotes": {
    "NQ=F": {
      "price": 30453.5,
      "change": -70.0,
      "pct": -0.23
    },
    "CL=F": {
      "price": 69.79,
      "change": 0.29,
      "pct": 0.42
    },
    "JPY=X": {
      "price": 162.81,
      "change": 0.29,
      "pct": 0.18
    },
    "^TNX": {
      "price": 4.467,
      "change": 0.045,
      "pct": 1.02
    },
    "^TYX": {
      "price": 4.958,
      "change": 0.055,
      "pct": 1.12
    },
    "DX-Y.NYB": {
      "price": 101.35,
      "change": 0.18,
      "pct": 0.18
    }
  },
  "errors": [],
  "fetched_at": "2026-07-01T12:55:51+09:00"
}