{
  "quotes": {
    "NQ=F": {
      "price": 29808.0,
      "change": 252.0,
      "pct": 0.85
    },
    "CL=F": {
      "price": 68.76,
      "change": 0.07,
      "pct": 0.1
    },
    "JPY=X": {
      "price": 161.96,
      "change": 0.58,
      "pct": 0.36
    },
    "^TNX": {
      "price": 4.47,
      "change": -0.009,
      "pct": -0.2
    },
    "^TYX": {
      "price": 4.974,
      "change": -0.007,
      "pct": -0.14
    },
    "DX-Y.NYB": {
      "price": 100.98,
      "change": 0.12,
      "pct": 0.12
    }
  },
  "errors": [],
  "fetched_at": "2026-07-06T14:17:15+09:00"
}