{
  "quotes": {
    "NQ=F": {
      "price": 29705.0,
      "change": 39.0,
      "pct": 0.13
    },
    "CL=F": {
      "price": 69.87,
      "change": -3.34,
      "pct": -4.56
    },
    "JPY=X": {
      "price": 161.75,
      "change": 0.24,
      "pct": 0.15
    },
    "^TNX": {
      "price": 4.416,
      "change": -0.072,
      "pct": -1.6
    },
    "^TYX": {
      "price": 4.864,
      "change": -0.078,
      "pct": -1.58
    },
    "DX-Y.NYB": {
      "price": 101.67,
      "change": 0.29,
      "pct": 0.29
    }
  },
  "errors": [],
  "fetched_at": "2026-06-24T23:00:59+09:00"
}