{
  "quotes": {
    "NQ=F": {
      "price": 28545.5,
      "change": -75.25,
      "pct": -0.26
    },
    "CL=F": {
      "price": 91.45,
      "change": -0.74,
      "pct": -0.8
    },
    "JPY=X": {
      "price": 163.79,
      "change": -0.06,
      "pct": -0.0366
    },
    "^TNX": {
      "price": 4.706,
      "change": 0.003,
      "pct": 0.0638
    },
    "^TYX": {
      "price": 5.175,
      "change": 0.004,
      "pct": 0.0774
    },
    "DX-Y.NYB": {
      "price": 101.438,
      "change": -0.006,
      "pct": -0.01
    },
    "^VIX": {
      "price": 18.7,
      "change": 0.0,
      "pct": 0.0
    }
  },
  "errors": [],
  "fetched_at": "2026-07-24T15:09:05+09:00",
  "jpy_carry": {
    "peak_3mo": 163.79,
    "warn_level": 158.88,
    "drop_pct": 0.0,
    "warning": false
  }
}