{
  "quotes": {
    "NQ=F": {
      "price": 30664.75,
      "change": -55.0,
      "pct": -0.18
    },
    "CL=F": {
      "price": 73.42,
      "change": -2.43,
      "pct": -3.2
    },
    "JPY=X": {
      "price": 161.21,
      "change": -0.1,
      "pct": -0.06
    },
    "^TNX": {
      "price": 4.496,
      "change": 0.043,
      "pct": 0.97
    },
    "^TYX": {
      "price": 4.936,
      "change": 0.035,
      "pct": 0.71
    }
  },
  "errors": [],
  "fetched_at": "2026-06-23T00:12:53+09:00"
}