{
  "quotes": {
    "NQ=F": {
      "price": 29879.5,
      "change": -214.75,
      "pct": -0.71
    },
    "CL=F": {
      "price": 68.13,
      "change": -0.45,
      "pct": -0.66
    },
    "JPY=X": {
      "price": 161.5,
      "change": -1.06,
      "pct": -0.65
    },
    "^TNX": {
      "price": 4.491,
      "change": 0.016,
      "pct": 0.36
    },
    "^TYX": {
      "price": 4.981,
      "change": 0.015,
      "pct": 0.3
    },
    "DX-Y.NYB": {
      "price": 101.19,
      "change": -0.23,
      "pct": -0.23
    }
  },
  "errors": [],
  "fetched_at": "2026-07-02T16:41:53+09:00"
}