{
  "quotes": {
    "NQ=F": {
      "price": 28560.5,
      "change": -620.75,
      "pct": -2.13
    },
    "CL=F": {
      "price": 92.63,
      "change": 5.8,
      "pct": 6.68
    },
    "JPY=X": {
      "price": 163.79,
      "change": 0.66,
      "pct": 0.4
    },
    "^TNX": {
      "price": 4.699,
      "change": 0.042,
      "pct": 0.9019
    },
    "^TYX": {
      "price": 5.168,
      "change": 0.021,
      "pct": 0.408
    },
    "DX-Y.NYB": {
      "price": 101.451,
      "change": 0.326,
      "pct": 0.32
    },
    "^VIX": {
      "price": 19.51,
      "change": 2.87,
      "pct": 17.25
    }
  },
  "errors": [],
  "fetched_at": "2026-07-24T03:30:11+09:00",
  "jpy_carry": {
    "peak_3mo": 163.79,
    "warn_level": 158.88,
    "drop_pct": 0.0,
    "warning": false
  }
}