{
  "quotes": {
    "NQ=F": {
      "price": 29073.5,
      "change": -107.75,
      "pct": -0.37
    },
    "CL=F": {
      "price": 90.22,
      "change": 3.39,
      "pct": 3.9
    },
    "JPY=X": {
      "price": 163.35,
      "change": 0.22,
      "pct": 0.13
    },
    "^TNX": {
      "price": 4.677,
      "change": 0.02,
      "pct": 0.4295
    },
    "^TYX": {
      "price": 5.165,
      "change": 0.018,
      "pct": 0.3497
    },
    "DX-Y.NYB": {
      "price": 101.138,
      "change": 0.013,
      "pct": 0.01
    },
    "^VIX": {
      "price": 17.62,
      "change": 0.98,
      "pct": 5.89
    }
  },
  "errors": [],
  "fetched_at": "2026-07-23T18:48:21+09:00",
  "jpy_carry": {
    "peak_3mo": 163.35,
    "warn_level": 158.45,
    "drop_pct": 0.0,
    "warning": false
  }
}