{
  "quotes": {
    "NQ=F": {
      "price": 29465.75,
      "change": 74.25,
      "pct": 0.25
    },
    "CL=F": {
      "price": 72.12,
      "change": 1.68,
      "pct": 2.39
    },
    "JPY=X": {
      "price": 162.37,
      "change": 0.39,
      "pct": 0.24
    },
    "^TNX": {
      "price": 4.553,
      "change": 0.024,
      "pct": 0.53
    },
    "^TYX": {
      "price": 5.059,
      "change": 0.016,
      "pct": 0.32
    },
    "DX-Y.NYB": {
      "price": 101.18,
      "change": 0.08,
      "pct": 0.08
    }
  },
  "errors": [],
  "fetched_at": "2026-07-08T10:54:47+09:00"
}