{
  "quotes": {
    "NQ=F": {
      "price": 29601.5,
      "change": 45.5,
      "pct": 0.15
    },
    "CL=F": {
      "price": 68.47,
      "change": -0.22,
      "pct": -0.32
    },
    "JPY=X": {
      "price": 161.28,
      "change": 0.27,
      "pct": 0.17
    },
    "^TNX": {
      "price": 4.46,
      "change": -0.018,
      "pct": -0.4
    },
    "^TYX": {
      "price": 4.985,
      "change": 0.004,
      "pct": 0.08
    },
    "DX-Y.NYB": {
      "price": 100.93,
      "change": 0.06,
      "pct": 0.06
    }
  },
  "errors": [],
  "fetched_at": "2026-07-03T09:56:11+09:00"
}