{
  "quotes": {
    "NQ=F": {
      "price": 30835.75,
      "change": -28.5,
      "pct": -0.09
    },
    "CL=F": {
      "price": 77.51,
      "change": -3.24,
      "pct": -4.01
    },
    "JPY=X": {
      "price": 160.33,
      "change": 0.02,
      "pct": 0.01
    },
    "^TNX": {
      "price": 4.437,
      "change": -0.028,
      "pct": -0.63
    },
    "^TYX": {
      "price": 4.938,
      "change": -0.032,
      "pct": -0.64
    }
  },
  "errors": [],
  "fetched_at": "2026-06-16T22:02:58+09:00"
}