{
  "quotes": {
    "NQ=F": {
      "price": 30536.25,
      "change": 483.5,
      "pct": 1.61
    },
    "CL=F": {
      "price": 69.74,
      "change": -1.01,
      "pct": -1.43
    },
    "JPY=X": {
      "price": 162.58,
      "change": 0.64,
      "pct": 0.4
    },
    "^TNX": {
      "price": 4.413,
      "change": 0.036,
      "pct": 0.82
    },
    "^TYX": {
      "price": 4.896,
      "change": 0.035,
      "pct": 0.72
    },
    "DX-Y.NYB": {
      "price": 101.21,
      "change": 0.08,
      "pct": 0.08
    }
  },
  "errors": [],
  "fetched_at": "2026-07-01T02:49:40+09:00"
}