{
  "quotes": {
    "NQ=F": {
      "price": 29665.0,
      "change": 196.5,
      "pct": 0.67
    },
    "CL=F": {
      "price": 73.13,
      "change": -0.39,
      "pct": -0.53
    },
    "JPY=X": {
      "price": 162.4,
      "change": -0.18,
      "pct": -0.11
    },
    "^TNX": {
      "price": 4.574,
      "change": 0.007,
      "pct": 0.15
    },
    "^TYX": {
      "price": 5.08,
      "change": 0.016,
      "pct": 0.32
    },
    "DX-Y.NYB": {
      "price": 100.97,
      "change": -0.1,
      "pct": -0.1
    }
  },
  "errors": [],
  "fetched_at": "2026-07-09T18:04:59+09:00"
}