{
  "quotes": {
    "NQ=F": {
      "price": 29121.25,
      "change": -60.0,
      "pct": -0.21
    },
    "CL=F": {
      "price": 88.37,
      "change": 1.54,
      "pct": 1.77
    },
    "JPY=X": {
      "price": 163.03,
      "change": -0.1,
      "pct": -0.0613
    },
    "^TNX": {
      "price": 4.661,
      "change": 0.004,
      "pct": 0.0859
    },
    "^TYX": {
      "price": 5.149,
      "change": 0.002,
      "pct": 0.0389
    },
    "DX-Y.NYB": {
      "price": 100.964,
      "change": -0.161,
      "pct": -0.16
    },
    "^VIX": {
      "price": 16.64,
      "change": -0.41,
      "pct": -2.4
    }
  },
  "errors": [],
  "fetched_at": "2026-07-23T13:24:05+09:00",
  "jpy_carry": {
    "peak_3mo": 163.03,
    "warn_level": 158.14,
    "drop_pct": 0.0,
    "warning": false
  }
}