{
  "quotes": {
    "NQ=F": {
      "price": 29686.25,
      "change": 221.5,
      "pct": 0.75
    },
    "CL=F": {
      "price": 84.45,
      "change": -3.26,
      "pct": -3.72
    },
    "JPY=X": {
      "price": 160.22,
      "change": 0.31,
      "pct": 0.19
    },
    "^TNX": {
      "price": 4.485,
      "change": 0.024,
      "pct": 0.54
    },
    "^TYX": {
      "price": 4.975,
      "change": 0.022,
      "pct": 0.44
    }
  },
  "errors": [],
  "fetched_at": "2026-06-13T04:01:33+09:00"
}