{
  "quotes": {
    "NQ=F": {
      "price": 30827.25,
      "change": -37.0,
      "pct": -0.12
    },
    "CL=F": {
      "price": 80.14,
      "change": -0.61,
      "pct": -0.76
    },
    "JPY=X": {
      "price": 160.22,
      "change": -0.09,
      "pct": -0.06
    },
    "^TNX": {
      "price": 4.459,
      "change": -0.006,
      "pct": -0.13
    },
    "^TYX": {
      "price": 4.968,
      "change": -0.002,
      "pct": -0.04
    }
  },
  "errors": [],
  "fetched_at": "2026-06-16T16:13:31+09:00"
}