{
  "quotes": {
    "NQ=F": {
      "price": 30557.25,
      "change": 602.5,
      "pct": 2.01
    },
    "CL=F": {
      "price": 80.44,
      "change": -4.44,
      "pct": -5.23
    },
    "JPY=X": {
      "price": 160.09,
      "change": -0.14,
      "pct": -0.09
    },
    "^TNX": {
      "price": 4.434,
      "change": -0.049,
      "pct": -1.09
    },
    "^TYX": {
      "price": 4.936,
      "change": -0.037,
      "pct": -0.74
    }
  },
  "errors": [],
  "fetched_at": "2026-06-15T16:49:30+09:00"
}