{
  "quotes": {
    "NQ=F": {
      "price": 30226.75,
      "change": -296.75,
      "pct": -0.97
    },
    "CL=F": {
      "price": 68.28,
      "change": -1.22,
      "pct": -1.76
    },
    "JPY=X": {
      "price": 162.39,
      "change": -0.13,
      "pct": -0.08
    },
    "^TNX": {
      "price": 4.46,
      "change": 0.038,
      "pct": 0.86
    },
    "^TYX": {
      "price": 4.96,
      "change": 0.057,
      "pct": 1.16
    },
    "DX-Y.NYB": {
      "price": 101.32,
      "change": 0.15,
      "pct": 0.15
    }
  },
  "errors": [],
  "fetched_at": "2026-07-02T00:02:54+09:00"
}