{
  "quotes": {
    "NQ=F": {
      "price": 28593.0,
      "change": -588.25,
      "pct": -2.02
    },
    "CL=F": {
      "price": 92.14,
      "change": 5.31,
      "pct": 6.12
    },
    "JPY=X": {
      "price": 163.78,
      "change": 0.65,
      "pct": 0.4
    },
    "^TNX": {
      "price": 4.703,
      "change": 0.046,
      "pct": 0.9878
    },
    "^TYX": {
      "price": 5.17,
      "change": 0.023,
      "pct": 0.4469
    },
    "DX-Y.NYB": {
      "price": 101.456,
      "change": 0.331,
      "pct": 0.33
    },
    "^VIX": {
      "price": 19.52,
      "change": 2.88,
      "pct": 17.31
    }
  },
  "errors": [],
  "fetched_at": "2026-07-24T03:45:22+09:00",
  "jpy_carry": {
    "peak_3mo": 163.78,
    "warn_level": 158.87,
    "drop_pct": 0.0,
    "warning": false
  }
}